blindx/__init__.py
blindx/__main__.py
blindx-0.1.9.dist-info/licenses/LICENSE
blindx-0.1.9.dist-info/METADATA
blindx-0.1.9.dist-info/WHEEL
blindx-0.1.9.dist-info/entry_points.txt
blindx-0.1.9.dist-info/top_level.txt
blindx-0.1.9.dist-info/RECORD
