Metadata-Version: 2.4
Name: blindx
Version: 0.1.9
Summary: Automated Blind XSS CLI Tool
Home-page: https://github.com/progprnv/blindx
Author: progprnv
License: MIT
Classifier: Programming Language :: Python :: 3
Classifier: License :: OSI Approved :: MIT License
Classifier: Operating System :: OS Independent
License-File: LICENSE
Requires-Dist: requests
Dynamic: license-file
